mrid/__init__.py
mrid/study.py
mrid/atlas/__init__.py
mrid/atlas/MNI152/__init__.py
mrid/atlas/SRI24/__init__.py
mrid/loading/__init__.py
mrid/loading/convert.py
mrid/preprocessing/CTseg.py
mrid/preprocessing/__init__.py
mrid/preprocessing/bias_field_correction.py
mrid/preprocessing/cropping.py
mrid/preprocessing/hd_bet.py
mrid/preprocessing/mask.py
mrid/preprocessing/simple_elastix.py
mrid/preprocessing/spatial.py
mrid/preprocessing/synthstrip.py
mrid/training/__init__.py
mrid/training/slicer.py
mrid/training/transforms.py
mrid/utils/__init__.py
mrid/utils/dcm2niix.py
mrid/utils/dicom_uid_fixer.py
mrid/utils/plotting.py
mrid/utils/python_utils.py
mrid/utils/stl_utils.py
mrid/utils/torch_utils.py
tests/test_loading.py
tests/test_preprocessing.py
tests/test_study.py
tests/test_utils.py
mrid_python-0.1.5.dist-info/METADATA
mrid_python-0.1.5.dist-info/WHEEL
mrid_python-0.1.5.dist-info/top_level.txt
mrid_python-0.1.5.dist-info/RECORD
