Metadata-Version: 2.4
Name: mrid-python
Version: 0.1.5
Summary: Tools for working with 3D medical images and segmentations - registration, brain skull-stripping, etc.
Author-email: Ivan Nikishev <nkshv2@gmail.com>
Project-URL: Homepage, https://github.com/inikishev/mrid
Project-URL: Repository, https://github.com/inikishev/mrid
Project-URL: Issues, https://github.com/inikishev/mrid/isses
Keywords: MRI,medical imaging
Requires-Python: >=3.10
Requires-Dist: numpy
Requires-Dist: SimpleITK
